Metadata-Version: 2.2
Name: ccompass
Version: 2.0.0
Summary: C-COMPASS (Cellular COMPartmentclASSifier) is an advanced open-source software tool designed for the quantitative analysis of fractionated proteomics samples.
Author-email: Daniel Haas <daniel.haas@helmholtz-munich.de>
License: BSD 3-Clause License
Project-URL: homepage, https://github.com/ICB-DCM/C-COMPASS
Project-URL: documentation, https://c-compass.readthedocs.io/en/latest/
Project-URL: issue-tracker, https://github.com/ICB-DCM/C-COMPASS/issues
Keywords: proteomics,machine learning,bioinformatics,mass spectrometry,fractionation
Classifier: Development Status :: 4 - Beta
Classifier: Intended Audience :: Science/Research
Classifier: License :: OSI Approved :: BSD License
Classifier: Operating System :: POSIX :: Linux
Classifier: Operating System :: MacOS :: MacOS X
Classifier: Operating System :: Microsoft :: Windows
Classifier: Programming Language :: Python
Classifier: Topic :: Scientific/Engineering :: Bio-Informatics
Requires-Python: >=3.10
License-File: LICENSE
Requires-Dist: FreeSimpleGUI
Requires-Dist: keras
Requires-Dist: keras-tuner
Requires-Dist: matplotlib
Requires-Dist: numpy
Requires-Dist: openpyxl
Requires-Dist: pandas
Requires-Dist: pydantic
Requires-Dist: pyyaml
Requires-Dist: rich
Requires-Dist: tensorflow
Requires-Dist: scikit-learn
Requires-Dist: scipy
Requires-Dist: seaborn
Requires-Dist: xlsxwriter
Provides-Extra: dev
Requires-Dist: pre-commit>=3; extra == "dev"
Requires-Dist: pytest; extra == "dev"
Requires-Dist: tox; extra == "dev"
Provides-Extra: doc
Requires-Dist: sphinx; extra == "doc"
Requires-Dist: sphinx-rtd-theme; extra == "doc"
Requires-Dist: sphinx-hoverxref; extra == "doc"
Requires-Dist: setuptools-scm; extra == "doc"
Provides-Extra: test
Requires-Dist: pytest; extra == "test"
